{
  "generated_at": "2025-08-30T11:41:35.095Z",
  "summary": {
    "total_sponsors": 33,
    "total_lifetime_amount": 1729.23,
    "total_current_monthly": 242,
    "special_sponsors": 7,
    "current_sponsors": 11,
    "past_sponsors": 15,
    "top_sponsor": {
      "name": "Steven Tey",
      "amount": 421
    }
  },
  "specialSponsors": [
    {
      "name": "Steven Tey",
      "githubId": "steven-tey",
      "avatarUrl": "https://avatars.githubusercontent.com/steven-tey",
      "websiteUrl": null,
      "githubUrl": "https://github.com/steven-tey",
      "tierName": "$421 one time",
      "totalProcessedAmount": 421,
      "sinceWhen": "since Jun 2025",
      "transactionCount": 1,
      "formattedAmount": "$421.00"
    },
    {
      "name": "Felipe Valencia",
      "githubId": "felipeva",
      "avatarUrl": "https://avatars.githubusercontent.com/felipeva",
      "websiteUrl": null,
      "githubUrl": "https://github.com/felipeva",
      "tierName": "$100 one time",
      "totalProcessedAmount": 220,
      "sinceWhen": "since Aug 2025",
      "transactionCount": 4,
      "formattedAmount": "$220.00"
    },
    {
      "name": "Brandon McConnell",
      "githubId": "brandonmcconnell",
      "avatarUrl": "https://avatars.githubusercontent.com/brandonmcconnell",
      "websiteUrl": null,
      "githubUrl": "https://github.com/brandonmcconnell",
      "tierName": "$100 one time",
      "totalProcessedAmount": 173.84,
      "sinceWhen": "since Jun 2025",
      "transactionCount": 3,
      "formattedAmount": "$173.84"
    },
    {
      "name": "vibecode",
      "githubId": "vibecode",
      "avatarUrl": "https://avatars.githubusercontent.com/vibecode",
      "websiteUrl": null,
      "githubUrl": "https://github.com/vibecode",
      "tierName": "$100 one time",
      "totalProcessedAmount": 100,
      "sinceWhen": "since Aug 2025",
      "transactionCount": 1,
      "formattedAmount": "$100.00"
    },
    {
      "name": "Clerk",
      "githubId": "clerkinc",
      "avatarUrl": "https://avatars.githubusercontent.com/clerkinc",
      "websiteUrl": null,
      "githubUrl": "https://github.com/clerkinc",
      "tierName": "$100 a month",
      "totalProcessedAmount": 100,
      "sinceWhen": "since Aug 2025",
      "transactionCount": 1,
      "formattedAmount": "$100.00"
    },
    {
      "name": "marckeelingiv",
      "githubId": "marckeelingiv",
      "avatarUrl": "https://avatars.githubusercontent.com/marckeelingiv",
      "websiteUrl": null,
      "githubUrl": "https://github.com/marckeelingiv",
      "tierName": "$100 one time",
      "totalProcessedAmount": 100,
      "sinceWhen": "since Aug 2025",
      "transactionCount": 1,
      "formattedAmount": "$100.00"
    },
    {
      "name": "Novu",
      "githubId": "novuhq",
      "avatarUrl": "https://avatars.githubusercontent.com/novuhq",
      "websiteUrl": null,
      "githubUrl": "https://github.com/novuhq",
      "tierName": "$100 a month",
      "totalProcessedAmount": 90.32,
      "sinceWhen": "since Aug 2025",
      "transactionCount": 1,
      "formattedAmount": "$90.32"
    }
  ],
  "sponsors": [
    {
      "name": "Bapusaheb Patil",
      "githubId": "bapspatil",
      "avatarUrl": "https://avatars.githubusercontent.com/bapspatil",
      "websiteUrl": null,
      "githubUrl": "https://github.com/bapspatil",
      "tierName": "$20 a month",
      "totalProcessedAmount": 120,
      "sinceWhen": "since May 2025",
      "transactionCount": 6,
      "formattedAmount": "$120.00"
    },
    {
      "name": "Ahmed Elsakaan",
      "githubId": "ixahmedxi",
      "avatarUrl": "https://avatars.githubusercontent.com/ixahmedxi",
      "websiteUrl": null,
      "githubUrl": "https://github.com/ixahmedxi",
      "tierName": "$5 a month",
      "totalProcessedAmount": 49.64,
      "sinceWhen": "since May 2025",
      "transactionCount": 1,
      "formattedAmount": "$49.64"
    },
    {
      "name": "Ali Hussein",
      "githubId": "Ali-Hussein-dev",
      "avatarUrl": "https://avatars.githubusercontent.com/Ali-Hussein-dev",
      "websiteUrl": null,
      "githubUrl": "https://github.com/Ali-Hussein-dev",
      "tierName": "$5 a month",
      "totalProcessedAmount": 10.5,
      "sinceWhen": "since Jul 2025",
      "transactionCount": 3,
      "formattedAmount": "$10.50"
    },
    {
      "name": "Yassir Touab",
      "githubId": "yassirtouab",
      "avatarUrl": "https://avatars.githubusercontent.com/yassirtouab",
      "websiteUrl": null,
      "githubUrl": "https://github.com/yassirtouab",
      "tierName": "$10 one time",
      "totalProcessedAmount": 10,
      "sinceWhen": "since Aug 2025",
      "transactionCount": 1,
      "formattedAmount": "$10.00"
    },
    {
      "name": "Avraj",
      "githubId": "notunderctrl",
      "avatarUrl": "https://avatars.githubusercontent.com/notunderctrl",
      "websiteUrl": null,
      "githubUrl": "https://github.com/notunderctrl",
      "tierName": "$10 one time",
      "totalProcessedAmount": 10,
      "sinceWhen": "since Aug 2025",
      "transactionCount": 1,
      "formattedAmount": "$10.00"
    },
    {
      "name": "Elber",
      "githubId": "elberrd",
      "avatarUrl": "https://avatars.githubusercontent.com/elberrd",
      "websiteUrl": null,
      "githubUrl": "https://github.com/elberrd",
      "tierName": "$10 one time",
      "totalProcessedAmount": 10,
      "sinceWhen": "since Aug 2025",
      "transactionCount": 1,
      "formattedAmount": "$10.00"
    },
    {
      "name": "Mohit Yadav",
      "githubId": "Just-Moh-it",
      "avatarUrl": "https://avatars.githubusercontent.com/Just-Moh-it",
      "websiteUrl": null,
      "githubUrl": "https://github.com/Just-Moh-it",
      "tierName": "$6 a month",
      "totalProcessedAmount": 8.32,
      "sinceWhen": "since Jul 2025",
      "transactionCount": 2,
      "formattedAmount": "$8.32"
    },
    {
      "name": "Mateus Santana",
      "githubId": "mateussmohamed",
      "avatarUrl": "https://avatars.githubusercontent.com/mateussmohamed",
      "websiteUrl": null,
      "githubUrl": "https://github.com/mateussmohamed",
      "tierName": "$5 one time",
      "totalProcessedAmount": 5,
      "sinceWhen": "since Aug 2025",
      "transactionCount": 1,
      "formattedAmount": "$5.00"
    },
    {
      "name": "Yannick Seeger",
      "githubId": "yk-sgr",
      "avatarUrl": "https://avatars.githubusercontent.com/yk-sgr",
      "websiteUrl": null,
      "githubUrl": "https://github.com/yk-sgr",
      "tierName": "$5 one time",
      "totalProcessedAmount": 5,
      "sinceWhen": "since Aug 2025",
      "transactionCount": 1,
      "formattedAmount": "$5.00"
    },
    {
      "name": "judikael bellance",
      "githubId": "jud3v2",
      "avatarUrl": "https://avatars.githubusercontent.com/jud3v2",
      "websiteUrl": null,
      "githubUrl": "https://github.com/jud3v2",
      "tierName": "$5 one time",
      "totalProcessedAmount": 5,
      "sinceWhen": "since Aug 2025",
      "transactionCount": 1,
      "formattedAmount": "$5.00"
    },
    {
      "name": "tn-py",
      "githubId": "tn-py",
      "avatarUrl": "https://avatars.githubusercontent.com/tn-py",
      "websiteUrl": null,
      "githubUrl": "https://github.com/tn-py",
      "tierName": "$1 a month",
      "totalProcessedAmount": 0.61,
      "sinceWhen": "since Aug 2025",
      "transactionCount": 1,
      "formattedAmount": "$0.61"
    }
  ],
  "pastSponsors": [
    {
      "name": "Better Stack Community",
      "githubId": "betterstack-community",
      "avatarUrl": "https://avatars.githubusercontent.com/betterstack-community",
      "websiteUrl": null,
      "githubUrl": "https://github.com/betterstack-community",
      "tierName": "$100 one time",
      "totalProcessedAmount": 100,
      "sinceWhen": "since Jul 2025",
      "transactionCount": 1,
      "formattedAmount": "$100.00"
    },
    {
      "name": "Cameron Pak",
      "githubId": "cameronapak",
      "avatarUrl": "https://avatars.githubusercontent.com/cameronapak",
      "websiteUrl": null,
      "githubUrl": "https://github.com/cameronapak",
      "tierName": "$50 one time",
      "totalProcessedAmount": 50,
      "sinceWhen": "since May 2025",
      "transactionCount": 1,
      "formattedAmount": "$50.00"
    },
    {
      "name": "Philip Yong",
      "githubId": "philipyong",
      "avatarUrl": "https://avatars.githubusercontent.com/philipyong",
      "websiteUrl": null,
      "githubUrl": "https://github.com/philipyong",
      "tierName": "$20 one time",
      "totalProcessedAmount": 20,
      "sinceWhen": "since Jun 2025",
      "transactionCount": 1,
      "formattedAmount": "$20.00"
    },
    {
      "name": "Guilherme Barros",
      "githubId": "gbarros-dev",
      "avatarUrl": "https://avatars.githubusercontent.com/gbarros-dev",
      "websiteUrl": null,
      "githubUrl": "https://github.com/gbarros-dev",
      "tierName": "$20 a month",
      "totalProcessedAmount": 20,
      "sinceWhen": "since May 2025",
      "transactionCount": 1,
      "formattedAmount": "$20.00"
    },
    {
      "name": "Alexander Swensen",
      "githubId": "AlexSwensen",
      "avatarUrl": "https://avatars.githubusercontent.com/AlexSwensen",
      "websiteUrl": null,
      "githubUrl": "https://github.com/AlexSwensen",
      "tierName": "$20 one time",
      "totalProcessedAmount": 20,
      "sinceWhen": "since May 2025",
      "transactionCount": 1,
      "formattedAmount": "$20.00"
    },
    {
      "name": "Mup",
      "githubId": "muperdev",
      "avatarUrl": "https://avatars.githubusercontent.com/muperdev",
      "websiteUrl": null,
      "githubUrl": "https://github.com/muperdev",
      "tierName": "$10 one time",
      "totalProcessedAmount": 10,
      "sinceWhen": "since Jul 2025",
      "transactionCount": 1,
      "formattedAmount": "$10.00"
    },
    {
      "name": "javayhu",
      "githubId": "javayhu",
      "avatarUrl": "https://avatars.githubusercontent.com/javayhu",
      "websiteUrl": null,
      "githubUrl": "https://github.com/javayhu",
      "tierName": "$10 one time",
      "totalProcessedAmount": 10,
      "sinceWhen": "since Jul 2025",
      "transactionCount": 1,
      "formattedAmount": "$10.00"
    },
    {
      "name": "Insik Han",
      "githubId": "Insik-Han",
      "avatarUrl": "https://avatars.githubusercontent.com/Insik-Han",
      "websiteUrl": null,
      "githubUrl": "https://github.com/Insik-Han",
      "tierName": "$10 one time",
      "totalProcessedAmount": 10,
      "sinceWhen": "since Jun 2025",
      "transactionCount": 1,
      "formattedAmount": "$10.00"
    },
    {
      "name": "Nick",
      "githubId": "nicolasguzca",
      "avatarUrl": "https://avatars.githubusercontent.com/nicolasguzca",
      "websiteUrl": null,
      "githubUrl": "https://github.com/nicolasguzca",
      "tierName": "$10 one time",
      "totalProcessedAmount": 10,
      "sinceWhen": "since Jun 2025",
      "transactionCount": 1,
      "formattedAmount": "$10.00"
    },
    {
      "name": "Igor Belogurov",
      "githubId": "bibblebabl",
      "avatarUrl": "https://avatars.githubusercontent.com/bibblebabl",
      "websiteUrl": null,
      "githubUrl": "https://github.com/bibblebabl",
      "tierName": "$10 one time",
      "totalProcessedAmount": 10,
      "sinceWhen": "since May 2025",
      "transactionCount": 1,
      "formattedAmount": "$10.00"
    },
    {
      "name": "Vadim Rusin",
      "githubId": "thevrus",
      "avatarUrl": "https://avatars.githubusercontent.com/thevrus",
      "websiteUrl": null,
      "githubUrl": "https://github.com/thevrus",
      "tierName": "$10 one time",
      "totalProcessedAmount": 10,
      "sinceWhen": "since May 2025",
      "transactionCount": 1,
      "formattedAmount": "$10.00"
    },
    {
      "name": "Piotr Kulpinski",
      "githubId": "piotrkulpinski",
      "avatarUrl": "https://avatars.githubusercontent.com/piotrkulpinski",
      "websiteUrl": null,
      "githubUrl": "https://github.com/piotrkulpinski",
      "tierName": "$5 one time",
      "totalProcessedAmount": 5,
      "sinceWhen": "since Jul 2025",
      "transactionCount": 1,
      "formattedAmount": "$5.00"
    },
    {
      "name": "feelswtc",
      "githubId": "feelswtc",
      "avatarUrl": "https://avatars.githubusercontent.com/feelswtc",
      "websiteUrl": null,
      "githubUrl": "https://github.com/feelswtc",
      "tierName": "$5 one time",
      "totalProcessedAmount": 5,
      "sinceWhen": "since Jul 2025",
      "transactionCount": 1,
      "formattedAmount": "$5.00"
    },
    {
      "name": "melodyclue",
      "githubId": "melodyclue",
      "avatarUrl": "https://avatars.githubusercontent.com/melodyclue",
      "websiteUrl": null,
      "githubUrl": "https://github.com/melodyclue",
      "tierName": "$5 one time",
      "totalProcessedAmount": 5,
      "sinceWhen": "since May 2025",
      "transactionCount": 1,
      "formattedAmount": "$5.00"
    },
    {
      "name": "Neville Brem",
      "githubId": "nevthereal",
      "avatarUrl": "https://avatars.githubusercontent.com/nevthereal",
      "websiteUrl": null,
      "githubUrl": "https://github.com/nevthereal",
      "tierName": "$5 one time",
      "totalProcessedAmount": 5,
      "sinceWhen": "since Apr 2025",
      "transactionCount": 1,
      "formattedAmount": "$5.00"
    }
  ]
}